LICENSE
MANIFEST.in
README.md
setup.cfg
setup.py
tgbot/__init__.py
tgbot/__main__.py
tgbot/botapi.py
tgbot/database.py
tgbot/database_migrations.py
tgbot/pluginbase.py
tgbot/plugintest.py
tgbot/tgbot.py
tgbot/webserver.py
tgbotplug.egg-info/PKG-INFO
tgbotplug.egg-info/SOURCES.txt
tgbotplug.egg-info/dependency_links.txt
tgbotplug.egg-info/pbr.json
tgbotplug.egg-info/requires.txt
tgbotplug.egg-info/top_level.txt