Metadata-Version: 1.1
Name: tgbotplug
Version: 1.2.10
Summary: Telegram plugin-based bot
Home-page: https://github.com/fopina/tgbotplug
Author: Filipe Pina
Author-email: fopina@skmobi.com
License: MIT License
Download-URL: https://github.com/fopina/tgbotplug/tarball/v1.2.10
Keywords: telegram,bot
Platform: UNKNOWN
Classifier: Development Status :: 4 - Beta
Classifier: Intended Audience :: Developers
Classifier: License :: OSI Approved :: MIT License
Classifier: Operating System :: OS Independent
Classifier: Programming Language :: Python
Classifier: Programming Language :: Python
Classifier: Programming Language :: Python :: 2
Classifier: Programming Language :: Python :: 2.7
